fastgac_pybind.cp38-win_amd64.pyd
fastgac/__init__.py
fastgac/__main__.py
fastgac/helper.py
fastgac/o3d_util.py
fastgac/peak_and_cluster.py
fastgac/scikit_image/LICENSE.txt
fastgac/scikit_image/__init__.py
fastgac/scikit_image/rank_order.py
fastgac/scikit_image/skimage_feature_peak.py
fastgac-1.0.5.dist-info/LICENSE
fastgac-1.0.5.dist-info/METADATA
fastgac-1.0.5.dist-info/WHEEL
fastgac-1.0.5.dist-info/top_level.txt
fastgac-1.0.5.dist-info/RECORD
