Metadata-Version: 2.1
Name: fastgac
Version: 1.0.5
Summary: Fast Gaussian Accumualtor. Detect dominant plane normals by integrating normals on a sphere.
Home-page: https://github.com/JeremyBYU/FastGaussianAccumulator
Author: Jeremy Castagno
Author-email: jeremybyu@gmail.com
License: MIT
Platform: UNKNOWN
License-File: LICENSE
Requires-Dist: numpy (>=1.15.0)
Requires-Dist: scipy (>=1.2.0)
